<item>
<title>Horror Sweet Home</title>
<thumbnail></thumbnail>
<fanart></fanart>
<link>http://ignoromo</link>
<urlsolve></urlsolve>
<externallink></externallink>
</item>

<item>
<title>Horror Sweet Home 2</title>
<thumbnail></thumbnail>
<fanart></fanart>
<link>http://ignoromo</link>
<urlsolve></urlsolve>
<externallink></externallink>
</item>


<item>
<title>Outlast 1&2</title>
<thumbnail></thumbnail>
<fanart></fanart>
<link>http://ignoromo</link>
<urlsolve></urlsolve>
<externallink></externallink>
</item>


<item>
<title>Visage</title>
<thumbnail></thumbnail>
<fanart></fanart>
<link>http://ignoromo</link>
<urlsolve></urlsolve>
<externallink></externallink>
</item>

